Workbook
Name aporte: Dashboard!$D$12
Name patrimonio: Dashboard!$D$15
Name qtd_anos: Dashboard!$D$13
Name rendimento_carteira: Dashboard!$D$8
Name salario: Dashboard!$D$7
Name sugestao_investimento: Dashboard!$D$9
Name taxa_mensal: Dashboard!$D$14

Sheet Dashboard
B2: SIMULADOR DE FUNDOS IMOBILIÁRIOS
B6: CONFIGURAÇÕES
B7: Salário | D7: 5000
B8: Rendimento Carteira | D8: 0.01
B9: Sugestão de Investimento (20%) | D9: =D7*20% -> 1000
B11: INVESTIMENTO MENSAL
B12: Quanto investir por mês ? | D12: 500
B13: Por Quantos Anos ? | D13: 25
B14: Taxa de Rendimento mensal ? | D14: 0.01
B15: Patrimônio acumulado ? | D15: =FV(taxa_mensal,qtd_anos*12,aporte*-1) -> 939423.31
B16: Dividendos Mensais ? | D16: =patrimonio*rendimento_carteira -> 9394.2331
B18: Cenários | D18: Dividendo
A19: 2 | B19: Quanto em 2 Anos ? | C19: =FV($D$14,$A19*12,$D$12*-1) -> 13486.732 | D19: =C19*rendimento_carteira -> 134.86732
A20: 5 | B20: Quanto em 5 Anos ? | C20: =FV($D$14,$A20*12,$D$12*-1) -> 40834.835 | D20: =C20*rendimento_carteira -> 408.34835
A21: 10 | B21: Quanto em 10 Anos ? | C21: =FV($D$14,$A21*12,$D$12*-1) -> 115019.34 | D21: =C21*rendimento_carteira -> 1150.1934
A22: 20 | B22: Quanto em 20 Anos ? | C22: =FV($D$14,$A22*12,$D$12*-1) -> 494627.68 | D22: =C22*rendimento_carteira -> 4946.2768
A23: 30 | B23: Quanto em 30 Anos ? | C23: =FV($D$14,$A23*12,$D$12*-1) -> 1747482.1 | D23: =C23*rendimento_carteira -> 17474.821
B25: PERFIL | C25: Conservador
B26: Valor a ser investido por mês | C26: =aporte -> 500
B28: TIPO DE FII | C28: Percentual Sugerido | D28: Valores
B29: PAPEL | C29: =VLOOKUP($C$25&"-"&B29,'Dados auxiliares'!$A:$D,4,FALSE) -> 0.4 | D29: =C29*$C$26 -> 200
B30: TIJOLO | C30: =VLOOKUP($C$25&"-"&B30,'Dados auxiliares'!$A:$D,4,FALSE) -> 0.35 | D30: =C30*$C$26 -> 175
B31: HÍBRIDOS | C31: =VLOOKUP($C$25&"-"&B31,'Dados auxiliares'!$A:$D,4,FALSE) -> 0.1 | D31: =C31*$C$26 -> 50
B32: FOFs | C32: =VLOOKUP($C$25&"-"&B32,'Dados auxiliares'!$A:$D,4,FALSE) -> 0.1 | D32: =C32*$C$26 -> 50
B33: DESENVOLVIMENTO | C33: =VLOOKUP($C$25&"-"&B33,'Dados auxiliares'!$A:$D,4,FALSE) -> 0.03 | D33: =C33*$C$26 -> 15
B34: HOTELARIAS | C34: =VLOOKUP($C$25&"-"&B34,'Dados auxiliares'!$A:$D,4,FALSE) -> 0.02 | D34: =C34*$C$26 -> 10
D35: =SUM(D29:D34) -> 500

Sheet Dados auxiliares
A2: CHAVE | B2: PERFIL | C2: TIPO DE FII | D2: %
A3: =B3&"-"&C3 -> Conservador-PAPEL | B3: Conservador | C3: PAPEL | D3: 0.4 | H3: %
A4: =B4&"-"&C4 -> Conservador-TIJOLO | B4: Conservador | C4: TIJOLO | D4: 0.35 | G4: Moderado-TIJOLO | H4: =VLOOKUP(G4,$A:$D,4,FALSE) -> 0.3
A5: =B5&"-"&C5 -> Conservador-HÍBRIDOS | B5: Conservador | C5: HÍBRIDOS | D5: 0.1
A6: =B6&"-"&C6 -> Conservador-FOFs | B6: Conservador | C6: FOFs | D6: 0.1
A7: =B7&"-"&C7 -> Conservador-DESENVOLVIMENTO | B7: Conservador | C7: DESENVOLVIMENTO | D7: 0.03
A8: =B8&"-"&C8 -> Conservador-HOTELARIAS | B8: Conservador | C8: HOTELARIAS | D8: 0.02
A9: =B9&"-"&C9 -> Moderado-PAPEL | B9: Moderado | C9: PAPEL | D9: 0.3
A10: =B10&"-"&C10 -> Moderado-TIJOLO | B10: Moderado | C10: TIJOLO | D10: 0.3
A11: =B11&"-"&C11 -> Moderado-HÍBRIDOS | B11: Moderado | C11: HÍBRIDOS | D11: 0.15
A12: =B12&"-"&C12 -> Moderado-FOFs | B12: Moderado | C12: FOFs | D12: 0.1
A13: =B13&"-"&C13 -> Moderado-DESENVOLVIMENTO | B13: Moderado | C13: DESENVOLVIMENTO | D13: 0.1
A14: =B14&"-"&C14 -> Moderado-HOTELARIAS | B14: Moderado | C14: HOTELARIAS | D14: 0.05
A15: =B15&"-"&C15 -> Agressivo-PAPEL | B15: Agressivo | C15: PAPEL | D15: 0.2
A16: =B16&"-"&C16 -> Agressivo-TIJOLO | B16: Agressivo | C16: TIJOLO | D16: 0.2
... A20: =B20&"-"&C20 -> Agressivo-HOTELARIAS | B20: Agressivo | C20: HOTELARIAS | D20: 0.1
